termforces/__main__.py
termforces/session_manager.py
termforces/termforces_shell.py
termforces/utils.py
termforces/cmds/__init__.py
termforces/cmds/fetch_samples.py
termforces/cmds/session_manager.py
termforces/cmds/submit_interface.py
termforces-0.1.2.data/scripts/termforces
termforces-0.1.2.dist-info/LICENSE
termforces-0.1.2.dist-info/METADATA
termforces-0.1.2.dist-info/WHEEL
termforces-0.1.2.dist-info/top_level.txt
termforces-0.1.2.dist-info/zip-safe
termforces-0.1.2.dist-info/RECORD
